queue_leu_leu/README.md
queue_leu_leu/__init__.py
queue_leu_leu/__main__.py
queue_leu_leu/arc/README.md
queue_leu_leu/arc/__init__.py
queue_leu_leu/arc/__main__.py
queue_leu_leu/arc/arc.py
queue_leu_leu/arc/example.py
queue_leu_leu/joint/README.md
queue_leu_leu/joint/__init__.py
queue_leu_leu/joint/__main__.py
queue_leu_leu/joint/example.py
queue_leu_leu/joint/joint.py
queue_leu_leu/orbit/README.md
queue_leu_leu/orbit/__init__.py
queue_leu_leu/orbit/__main__.py
queue_leu_leu/orbit/example.py
queue_leu_leu/orbit/orbit.py
queue_leu_leu/polygon/README.md
queue_leu_leu/polygon/__init__.py
queue_leu_leu/polygon/__main__.py
queue_leu_leu/polygon/example.py
queue_leu_leu/polygon/polygon.py
queue_leu_leu/square/README.md
queue_leu_leu/square/__init__.py
queue_leu_leu/square/__main__.py
queue_leu_leu/square/example.py
queue_leu_leu/square/square.py
queue_leu_leu/trail/README.md
queue_leu_leu/trail/__init__.py
queue_leu_leu/trail/__main__.py
queue_leu_leu/trail/example.py
queue_leu_leu/trail/trail.py
queue_leu_leu-1.1.dist-info/licenses/LICENCE.txt
queue_leu_leu-1.1.dist-info/METADATA
queue_leu_leu-1.1.dist-info/WHEEL
queue_leu_leu-1.1.dist-info/top_level.txt
queue_leu_leu-1.1.dist-info/RECORD
