Metadata-Version: 2.4
Name: queue_leu_leu
Version: 1.1
Summary: Collection of Python scripts, showing minimal examples of objects following each other.
Home-page: https://github.com/xorblo-doitus/queue_leu_leu
Author: ZetaMap, xorblo-doitus
License: MIT
Project-URL: GitHub Project, https://github.com/xorblo-doitus/queue_leu_leu
Project-URL: ZetaMap, https://github.com/ZetaMap/
Project-URL: xorblo-doitus, https://github.com/xorblo-doitus
Classifier: Programming Language :: Python :: 3
Classifier: License :: OSI Approved :: MIT License
Classifier: Operating System :: Microsoft :: Windows
Classifier: Operating System :: Unix
Classifier: Operating System :: MacOS :: MacOS X
Requires-Python: >=3.9
License-File: LICENCE.txt
Requires-Dist: pygame
Dynamic: author
Dynamic: classifier
Dynamic: description
Dynamic: description-content-type
Dynamic: home-page
Dynamic: license
Dynamic: license-file
Dynamic: project-url
Dynamic: requires-dist
Dynamic: requires-python
Dynamic: summary
